pyssianutils/__init__.py
pyssianutils/_version.py
pyssianutils/initialize.py
pyssianutils/pyssianutils
pyssianutils/toxyz.py
pyssianutils/utils.py
pyssianutils/input/__init__.py
pyssianutils/input/asinput.py
pyssianutils/input/distortts.py
pyssianutils/input/inputht.py
pyssianutils/others/__init__.py
pyssianutils/others/cubestddft.py
pyssianutils/others/track.py
pyssianutils/plot/__init__.py
pyssianutils/plot/optmulti.py
pyssianutils/plot/optview.py
pyssianutils/plot/property.py
pyssianutils/print/__init__.py
pyssianutils/print/potential.py
pyssianutils/print/summary.py
pyssianutils/print/thermo.py
pyssianutils/resources/defaults.ini
pyssianutils/resources/templates/slurm/example.json
pyssianutils/resources/templates/slurm/example.txt
pyssianutils/submit/__init__.py
pyssianutils/submit/custom.py
pyssianutils/submit/slurm.py
pyssianutils-1.0.2.data/scripts/pyssianutils
pyssianutils-1.0.2.dist-info/licenses/LICENSE
pyssianutils-1.0.2.dist-info/METADATA
pyssianutils-1.0.2.dist-info/WHEEL
pyssianutils-1.0.2.dist-info/top_level.txt
pyssianutils-1.0.2.dist-info/RECORD
