Metadata-Version: 2.4
Name: pyssianutils
Version: 1.0.2
Summary: A CLI with utils for everyday tasks in CompChem developed with pyssian
Home-page: https://github.com/maserasgroup-repo/pyssian-utils
Author: Raúl Pérez-Soto
Author-email: rperezsoto.research@gmail.com
Project-URL: Bug Reports, https://github.com/maserasgroup-repo/pyssian-utils/issues
Project-URL: Source, https://github.com/maserasgroup-repo/pyssian-utils
Project-URL: Docs, https://maserasgroup-repo.github.io/pyssian-utils/
Keywords: compchem,gaussian,parser
Classifier: Programming Language :: Python :: 3
Classifier: Programming Language :: Python :: 3.12
Requires-Python: >=3.10
License-File: LICENSE
Requires-Dist: setuptools
Requires-Dist: pathlib
Requires-Dist: numpy
Requires-Dist: pyssian>=1.1
Requires-Dist: platformdirs
Provides-Extra: plotting
Requires-Dist: matplotlib; extra == "plotting"
Requires-Dist: plotly; extra == "plotting"
Dynamic: author
Dynamic: author-email
Dynamic: classifier
Dynamic: description
Dynamic: description-content-type
Dynamic: home-page
Dynamic: keywords
Dynamic: license-file
Dynamic: project-url
Dynamic: provides-extra
Dynamic: requires-dist
Dynamic: requires-python
Dynamic: summary
